plugin.cmake
setup.py
girder_metadata_history/__init__.py
girder_metadata_history/constants.py
girder_metadata_history/resource.py
girder_metadata_history.egg-info/PKG-INFO
girder_metadata_history.egg-info/SOURCES.txt
girder_metadata_history.egg-info/dependency_links.txt
girder_metadata_history.egg-info/entry_points.txt
girder_metadata_history.egg-info/not-zip-safe
girder_metadata_history.egg-info/requires.txt
girder_metadata_history.egg-info/top_level.txt
girder_metadata_history/web_client/main.js
girder_metadata_history/web_client/package.json
girder_metadata_history/web_client/routes.js
girder_metadata_history/web_client/templates/configView.pug
girder_metadata_history/web_client/views/ConfigView.js
plugin_tests/__init__.py
plugin_tests/provenanceSpec.js
plugin_tests/provenance_test.py