Metadata-Version: 1.1
Name: girder-metadata-history
Version: 0.2.0a1
Summary: Tracks metadata history of items in Girder
Home-page: UNKNOWN
Author: Kitware, Inc.
Author-email: kitware@kitware.com
License: Apache 2.0
Platform: UNKNOWN
Classifier: Development Status :: 4 - Beta
Classifier: Environment :: Web Environment
Classifier: License :: OSI Approved :: Apache Software License
Classifier: Operating System :: OS Independent
Classifier: Programming Language :: Python
Classifier: Programming Language :: Python :: 2
Classifier: Programming Language :: Python :: 2.7
Classifier: Programming Language :: Python :: 3
Classifier: Programming Language :: Python :: 3.5
